cdrc/__init__.py
cdrc/common.py
cdrc/dev/__init__.py
cdrc/dev/script.py
cdrc/main.py
cdrc/schemas.py
cdrc/scripts/format.sh
cdrc-0.1.15.dist-info/LICENSE
cdrc-0.1.15.dist-info/METADATA
cdrc-0.1.15.dist-info/WHEEL
cdrc-0.1.15.dist-info/entry_points.txt
cdrc-0.1.15.dist-info/RECORD
