Metadata-Version: 2.1
Name: cdrc
Version: 0.1.15
Summary: 
Author: marshHawk4
Author-email: kyle@jataware.com
Requires-Python: >=3.10,<4.0
Classifier: Programming Language :: Python :: 3
Classifier: Programming Language :: Python :: 3.10
Classifier: Programming Language :: Python :: 3.11
Classifier: Programming Language :: Python :: 3.12
Requires-Dist: geopandas (>=1.0.1,<2.0.0)
Requires-Dist: httpx (==0.27.*)
Requires-Dist: numpy (==1.26.2)
Requires-Dist: pydantic (>=2.8.0,<3.0.0)
Requires-Dist: wand (>=0.6.13,<0.7.0)
